wand_client/__init__.py
wand_client/jupyter.py
wand_client/cli/__init__.py
wand_client/cli/config.py
wand_client/cli/formatters.py
wand_client/cli/main.py
wand_client/sdk/__init__.py
wand_client/sdk/core.py
wand_ai_client-0.0.9.dist-info/METADATA
wand_ai_client-0.0.9.dist-info/WHEEL
wand_ai_client-0.0.9.dist-info/entry_points.txt
wand_ai_client-0.0.9.dist-info/top_level.txt
wand_ai_client-0.0.9.dist-info/RECORD
