Metadata-Version: 2.1
Name: wand-ai-client
Version: 0.0.9
Summary: Wand AI API client
Author: Wand.AI Team
Classifier: Programming Language :: Python :: 3
Classifier: Programming Language :: Python :: 3.8
Classifier: Programming Language :: Python :: 3.9
Classifier: Programming Language :: Python :: 3.10
Classifier: Programming Language :: Python :: 3.11
Classifier: Operating System :: OS Independent
Classifier: Development Status :: 4 - Beta
Classifier: Environment :: Console
Classifier: Intended Audience :: Developers
Classifier: Intended Audience :: Science/Research
Classifier: Intended Audience :: Information Technology
Classifier: Topic :: Scientific/Engineering :: Artificial Intelligence
Classifier: Topic :: Software Development
Classifier: Topic :: Utilities
Requires-Python: >=3.8.0
Requires-Dist: click (>=8.0)
Requires-Dist: rich (>=11.0.0)
Requires-Dist: requests (>=2.27.0)
Requires-Dist: pydantic (>=1.10.0)
Requires-Dist: prompt-toolkit (>=3.0.0)
Provides-Extra: dev
Requires-Dist: mypy (==1.3.0) ; extra == 'dev'
Requires-Dist: pre-commit (==3.3.2) ; extra == 'dev'
Requires-Dist: codecov (==2.1.13) ; extra == 'dev'
Requires-Dist: docker (==6.1.2) ; extra == 'dev'
Requires-Dist: pytest (==7.3.1) ; extra == 'dev'
Requires-Dist: pytest-asyncio (==0.21.0) ; extra == 'dev'
Requires-Dist: pytest-cov (==4.1.0) ; extra == 'dev'
Requires-Dist: types-requests (==2.31.0.0) ; extra == 'dev'
